rtl/single_cycle/data/alu.sv
module alu #(
    parameter WIDTH = 32
)(
    input   logic [WIDTH-1:0]     ALUop1,
    input   logic [WIDTH-1:0]     ALUop2,
    input   logic [2:0]           ALUctrl,
    output  logic [WIDTH-1:0]     SUM,
    output  logic                 EQ
);

    // changed from 32'd255 to take that operand as t1, so that bnez also works

always_comb begin
    case (ALUctrl)
      3'b000: begin
        // ALU control is 3'b000, so perform addition
        SUM <= ALUop1 + ALUop2;
        EQ <= EQ; // Set EQ to 0 (not used in this case)
      end
      3'b001: begin
        // ALU control is 3'b001, so check for equality
        EQ <= (ALUop1 == ALUop2) ? 1 : 0;
        SUM <= 0; // Set SUM to 0 (not used in this case)
      end
      default: begin
        // Handle other cases if needed
        SUM <= 0;
        EQ <= 0;
      end
    endcase
  end
     
endmodule

rtl/pipelined/data/alu_src_mux.sv
module alu_src_mux #(
    parameter WIDTH = 32
)
(
    input logic[WIDTH-1:0] d0, d1,
    input logic             ALUsrc,
    output logic [WIDTH-1:0] y
    );
    assign y = ALUsrc ? d1 : d0;
endmodule

rtl/single_cycle/data/register_file.sv
module regfile #(
    parameter WIDTH = 5,
    parameter DATAWIDTH = 32
)(
    input   logic  [WIDTH-1:0]     AD1, 
    input   logic  [WIDTH-1:0]     AD2,
    input   logic  [WIDTH-1:0]     AD3,
    input   logic                  WE3,
    input   logic  [DATAWIDTH-1:0] WD3,
    input   logic                  clk,
    output  logic  [DATAWIDTH-1:0] RD1,
    output  logic  [DATAWIDTH-1:0] RD2,
    output  logic  [DATAWIDTH-1:0] a0,
    output logic   [DATAWIDTH-1:0] a1, // added for debugging
    output logic   [DATAWIDTH-1:0] t1  // added for debugging   
);

logic [DATAWIDTH-1:0] registers [31:0];



    always_ff @(posedge clk) begin
        if (WE3 == 1'b1) begin
            registers[AD3] <= WD3; //RESULT FROM ALU IS STORED IN ADDRESS 3
        end
    end

    always_comb
    begin
        RD1 <= registers[AD1]; // DATA IS READ FROM AD1 AND AD2
        RD2 <= registers[AD2];
        a0 <=  registers[5'b01010]; // a0 is output which is set to result
        a1 <=  registers[5'b01011];
        t1 <=  registers[5'b00110];
    end


endmodule

rtl/single_cycle/data/data_top_level.sv
module data_top_level #(
    parameter REGWIDTH = 5,
    parameter DATAWIDTH = 32
)(
    input logic                     clk,
    input logic  [REGWIDTH-1:0]     rs1,
    input logic  [REGWIDTH-1:0]     rs2,
    input logic  [REGWIDTH-1:0]     rd,
    input logic                     RegWrite,
    //input logic  [DATAWIDTH-1:0]    ALUop1,
    //input logic  [DATAWIDTH-1:0]    regOp2,
    //input logic  [DATAWIDTH-1:0]    ALUop2,
    input logic                     ALUsrc,
    input logic  [2:0]              ALUctrl,
    input logic  [DATAWIDTH-1:0]    ImmOp,
    //output logic [DATAWIDTH-1:0]    ALUout,
    output logic                    EQ,
    output logic [DATAWIDTH-1:0]    a0,
    output logic [DATAWIDTH-1:0]    ALUop1 // used exclusively for jalr
);

// logic [DATAWIDTH-1:0]               ALUop1;
logic [DATAWIDTH-1:0]               regOp2;
logic [DATAWIDTH-1:0]               ALUop2;
logic [DATAWIDTH-1:0]               ALUout;

regfile register(
    .AD1(rs1),
    .AD2(rs2),
    .AD3(rd),
    .WE3(RegWrite),
    .WD3(ALUout),
    .clk(clk),
    .RD1(ALUop1),
    .RD2(regOp2),
    .a0(a0)
);

alu_src_mux multi(
    .d0 (regOp2),
    .d1 (ImmOp),
    .ALUsrc (ALUsrc),
    .y (ALUop2)
);

alu ALU(
    .ALUop1 (ALUop1),
    .ALUop2 (ALUop2),
    .ALUctrl (ALUctrl),
    .SUM (ALUout),
    .EQ (EQ)
);

endmodule

rtl/single_cycle/control/extend.sv
module signextend #(
    parameter WIDTH = 32
)(
    input logic              Immsrc,
    input logic [WIDTH-1:0]  instr,
    output logic [WIDTH-1:0] Immop
);

    assign Immop = Immsrc ? {{20{instr[31]}}, instr[31:20]} : {{20{instr[31]}}, instr[7], instr[30:25], instr[11:8], 1'b0};
    

endmodule

rtl/single_cycle/control/control_unit.sv
module controlunit (
    input logic                 EQ,
    input logic [6:0]           opcode,
    output logic                RegWrite,
    output logic [2:0]          ALUctrl, // changed from [3:0]
    output logic                ALUsrc,
    output logic                ImmSrc,
    output logic                PCSrc
);
always_comb begin
    if (opcode == 7'b1100011) // B-type instruction - branch not equals
        begin
            ALUctrl  <= 3'b001; //B-type signal
            ALUsrc   <= 0;
            RegWrite <= 0;
            PCSrc <= ~(EQ);
            ImmSrc <= 0;
        end
    
    else if (opcode == 7'b0010011)// I-type instruction - addi instruction
        begin
            ALUctrl  <= 3'b000; //I-type signal
            ALUsrc   <= 1;
            RegWrite <= 1;
            PCSrc    <= 0;
            ImmSrc <= 1;
        end
    
    // EQ = 0;
end

endmodule

rtl/single_cycle/control/instruction_memory.sv
module instrmem #(
    parameter ADDRESS_WIDTH = 32,
              DATA_WIDTH = 8
)(
    input logic [ADDRESS_WIDTH-1:0] A, //would be the memory address
    output logic [ADDRESS_WIDTH-1:0]   RD //instruction word 
);

    logic [DATA_WIDTH-1:0] instr_array [2**DATA_WIDTH-1:0];

initial begin
    $display("Loading instr.");
    $readmemh("instrrom.mem", instr_array);
end

always_comb begin
    RD = {instr_array[A], instr_array[A+1], instr_array[A+2], instr_array[A+3]}; //implements asynchronous reset
end

endmodule

rtl/single_cycle/program_counter/pc_reg.sv
module pc_reg #(
    parameter WIDTH = 32
)(
    input   logic               clk,    // clock
    input   logic               rst,    // reset
    input   logic   [WIDTH-1:0] pcin,   // 32-bit input pc
    output   logic  [WIDTH-1:0] pcout   // 32-bit output pc
);

    logic   [WIDTH-1:0]           PCreg;    // 32-bit register

    always_ff @(posedge clk or posedge rst)
    begin
        if (rst)
            PCreg <= 32'b0;
        else
            PCreg <= pcin;
    end

    assign pcout = PCreg; // fixed pc delay

endmodule

rtl/single_cycle/program_counter/pc_module.sv
module pc_module #(
    parameter WIDTH = 32
)(
    input   logic               clk,    // clock
    input   logic               rst,    // reset
    input   logic   [WIDTH-1:0] ImmOp,  // 32-bit immediate to make a pc jump
    input   logic               PCsrc,  // determined whether pc is +4 or +ImmOp
    output  logic   [WIDTH-1:0] PC      // program counter
);

    logic   [WIDTH-1:0]           branch_PC;    // branch pc ie. pc + immop
    logic   [WIDTH-1:0]           inc_PC;       // increased pc ie. pc + 4
    logic   [WIDTH-1:0]           next_PC;      // next program counter

always_comb begin
    if (rst)
        next_PC <= 32'b0; // resolved wrong value after reset problem
    else begin
        branch_PC <= PC + ImmOp;
        inc_PC <= PC + 32'd4;
        next_PC <= (PCsrc) ? branch_PC : inc_PC;
    end
end

pc_reg mypc_reg (
    .clk (clk),
    .rst (rst),
    .pcin (next_PC),
    .pcout (PC)
);

endmodule

rtl/single_cycle/toplevel.sv
/*
Five main sub components: 
1. "program_counter" : Program Counter and related adders.
2, 3, 4. control_module : The Control Unit, the Sign-extension Unit and the instruction memory.
    2. "control_unit"
    3. "instruction_memory"
    4. "sign_extend"
5. "alu_and_registers" : The Register File, ALU and the related MUX.
*/ 


module toplevel #(
    parameter WIDTH = 32
)(
    input logic                     clk,
    input logic                     rst,            
    output logic [WIDTH-1:0]        a0              // measured output of program
);

// inerconnecting signals
logic [WIDTH-1:0]                   PC;             // from pc_module to control_module)
logic [WIDTH-1:0]                   instr;          // output of the instruction memory - the instruction
logic [WIDTH-1:0]                   ImmOp;          // from control_module to alu_module and from control_module to pc_module
logic                               ImmSrc;         // From control unit to Sign Extend
//unused logic [4:0]                         rs1;            // from control_module to alu_module
//unused logic [4:0]                         rs2;            // from control_module to alu_module
//unused logic [4:0]                         rd;             // from control_module to alu_module
logic                               RegWrite;       // from control_module to alu_module
logic [2:0]                         ALUctrl;        // from control_module to alu_module
logic                               ALUsrc;         // from control_module to alu_module
logic                               PCsrc;          // from control_module to pc_module
logic                               EQ;             // from alu_module to control_module

pc_module program_counter(
    .clk(clk),
    .rst(rst),
    .ImmOp (ImmOp),
    .PCsrc (PCsrc),
    .PC (PC)
);


instrmem instruction_memory(
    .A(PC),
    .RD(instr)
);


controlunit control_unit(
    .EQ(EQ),
    .opcode(instr[6:0]),
    .RegWrite(RegWrite),
    .ALUctrl(ALUctrl),
    .ALUsrc(ALUsrc),
    .ImmSrc(ImmSrc),
    .PCSrc(PCsrc)
);


signextend sign_extend(
    .Immsrc(ImmSrc),
    .instr(instr),
    .Immop(ImmOp)
);


data_top_level alu_and_registers(
    .clk(clk),
    .rs1 (instr[19:15]),
    .rs2 (instr[24:20]),
    .rd (instr[11:7]),
    .RegWrite (RegWrite),
    .ALUctrl(ALUctrl),
    .ALUsrc (ALUsrc),
    .ImmOp (ImmOp),
    .EQ (EQ),
    .a0(a0)
);

endmodule

rtl/single_cycle/toplevel.vcd
$version Generated by VerilatedVcd $end
$date Mon Nov 27 18:31:26 2023 $end
$timescale 1ps $end

 $scope module TOP $end
  $var wire 32 Y a0 [31:0] $end
  $var wire  1 W clk $end
  $var wire  1 X rst $end
  $scope module toplevel $end
   $var wire  3 I ALUctrl [2:0] $end
   $var wire  1 J ALUsrc $end
   $var wire  1 L EQ $end
   $var wire 32 F ImmOp [31:0] $end
   $var wire  1 G ImmSrc $end
   $var wire 32 Z PC [31:0] $end
   $var wire  1 K PCsrc $end
   $var wire  1 H RegWrite $end
   $var wire 32 \ WIDTH [31:0] $end
   $var wire 32 Y a0 [31:0] $end
   $var wire  1 W clk $end
   $var wire 32 E instr [31:0] $end
   $var wire  1 X rst $end
   $scope module alu_and_registers $end
    $var wire  3 I ALUctrl [2:0] $end
    $var wire 32 P ALUop1 [31:0] $end
    $var wire 32 Q ALUop2 [31:0] $end
    $var wire 32 R ALUout [31:0] $end
    $var wire  1 J ALUsrc $end
    $var wire 32 \ DATAWIDTH [31:0] $end
    $var wire  1 L EQ $end
    $var wire 32 F ImmOp [31:0] $end
    $var wire 32 ] REGWIDTH [31:0] $end
    $var wire  1 H RegWrite $end
    $var wire 32 Y a0 [31:0] $end
    $var wire  1 W clk $end
    $var wire  5 O rd [4:0] $end
    $var wire 32 [ regOp2 [31:0] $end
    $var wire  5 M rs1 [4:0] $end
    $var wire  5 N rs2 [4:0] $end
    $scope module ALU $end
     $var wire  3 I ALUctrl [2:0] $end
     $var wire 32 P ALUop1 [31:0] $end
     $var wire 32 Q ALUop2 [31:0] $end
     $var wire  1 L EQ $end
     $var wire 32 R SUM [31:0] $end
     $var wire 32 \ WIDTH [31:0] $end
    $upscope $end
    $scope module multi $end
     $var wire  1 J ALUsrc $end
     $var wire 32 \ WIDTH [31:0] $end
     $var wire 32 [ d0 [31:0] $end
     $var wire 32 F d1 [31:0] $end
     $var wire 32 Q y [31:0] $end
    $upscope $end
    $scope module register $end
     $var wire  5 M AD1 [4:0] $end
     $var wire  5 N AD2 [4:0] $end
     $var wire  5 O AD3 [4:0] $end
     $var wire 32 \ DATAWIDTH [31:0] $end
     $var wire 32 P RD1 [31:0] $end
     $var wire 32 [ RD2 [31:0] $end
     $var wire 32 R WD3 [31:0] $end
     $var wire  1 H WE3 $end
     $var wire 32 ] WIDTH [31:0] $end
     $var wire 32 Y a0 [31:0] $end
     $var wire 32 # a1 [31:0] $end
     $var wire  1 W clk $end
     $var wire 32 % registers[0] [31:0] $end
     $var wire 32 / registers[10] [31:0] $end
     $var wire 32 0 registers[11] [31:0] $end
     $var wire 32 1 registers[12] [31:0] $end
     $var wire 32 2 registers[13] [31:0] $end
     $var wire 32 3 registers[14] [31:0] $end
     $var wire 32 4 registers[15] [31:0] $end
     $var wire 32 5 registers[16] [31:0] $end
     $var wire 32 6 registers[17] [31:0] $end
     $var wire 32 7 registers[18] [31:0] $end
     $var wire 32 8 registers[19] [31:0] $end
     $var wire 32 & registers[1] [31:0] $end
     $var wire 32 9 registers[20] [31:0] $end
     $var wire 32 : registers[21] [31:0] $end
     $var wire 32 ; registers[22] [31:0] $end
     $var wire 32 < registers[23] [31:0] $end
     $var wire 32 = registers[24] [31:0] $end
     $var wire 32 > registers[25] [31:0] $end
     $var wire 32 ? registers[26] [31:0] $end
     $var wire 32 @ registers[27] [31:0] $end
     $var wire 32 A registers[28] [31:0] $end
     $var wire 32 B registers[29] [31:0] $end
     $var wire 32 ' registers[2] [31:0] $end
     $var wire 32 C registers[30] [31:0] $end
     $var wire 32 D registers[31] [31:0] $end
     $var wire 32 ( registers[3] [31:0] $end
     $var wire 32 ) registers[4] [31:0] $end
     $var wire 32 * registers[5] [31:0] $end
     $var wire 32 + registers[6] [31:0] $end
     $var wire 32 , registers[7] [31:0] $end
     $var wire 32 - registers[8] [31:0] $end
     $var wire 32 . registers[9] [31:0] $end
     $var wire 32 $ t1 [31:0] $end
    $upscope $end
   $upscope $end
   $scope module control_unit $end
    $var wire  3 I ALUctrl [2:0] $end
    $var wire  1 J ALUsrc $end
    $var wire  1 L EQ $end
    $var wire  1 G ImmSrc $end
    $var wire  1 K PCSrc $end
    $var wire  1 H RegWrite $end
    $var wire  7 S opcode [6:0] $end
   $upscope $end
   $scope module instruction_memory $end
    $var wire 32 Z A [31:0] $end
    $var wire 32 \ ADDRESS_WIDTH [31:0] $end
    $var wire 32 ^ DATA_WIDTH [31:0] $end
    $var wire 32 E RD [31:0] $end
   $upscope $end
   $scope module program_counter $end
    $var wire 32 F ImmOp [31:0] $end
    $var wire 32 Z PC [31:0] $end
    $var wire  1 K PCsrc $end
    $var wire 32 \ WIDTH [31:0] $end
    $var wire 32 T branch_PC [31:0] $end
    $var wire  1 W clk $end
    $var wire 32 U inc_PC [31:0] $end
    $var wire 32 V next_PC [31:0] $end
    $var wire  1 X rst $end
    $scope module mypc_reg $end
     $var wire 32 Z PCreg [31:0] $end
     $var wire 32 \ WIDTH [31:0] $end
     $var wire  1 W clk $end
     $var wire 32 V pcin [31:0] $end
     $var wire 32 Z pcout [31:0] $end
     $var wire  1 X rst $end
    $upscope $end
   $upscope $end
   $scope module sign_extend $end
    $var wire 32 F Immop [31:0] $end
    $var wire  1 G Immsrc $end
    $var wire 32 \ WIDTH [31:0] $end
    $var wire 32 E instr [31:0] $end
   $upscope $end
  $upscope $end
 $upscope $end
$enddefinitions $end


#0
b00000000000000000000000000000000 #
b00000000000000000000000000000000 $
b00000000000000000000000000000000 %
b00000000000000000000000000000000 &
b00000000000000000000000000000000 '
b00000000000000000000000000000000 (
b00000000000000000000000000000000 )
b00000000000000000000000000000000 *
b00000000000000000000000000000000 +
b00000000000000000000000000000000 ,
b00000000000000000000000000000000 -
b00000000000000000000000000000000 .
b00000000000000000000000000000000 /
b00000000000000000000000000000000 0
b00000000000000000000000000000000 1
b00000000000000000000000000000000 2
b00000000000000000000000000000000 3
b00000000000000000000000000000000 4
b00000000000000000000000000000000 5
b00000000000000000000000000000000 6
b00000000000000000000000000000000 7
b00000000000000000000000000000000 8
b00000000000000000000000000000000 9
b00000000000000000000000000000000 :
b00000000000000000000000000000000 ;
b00000000000000000000000000000000 <
b00000000000000000000000000000000 =
b00000000000000000000000000000000 >
b00000000000000000000000000000000 ?
b00000000000000000000000000000000 @
b00000000000000000000000000000000 A
b00000000000000000000000000000000 B
b00000000000000000000000000000000 C
b00000000000000000000000000000000 D
b00000000000000000000000000000000 E
b00000000000000000000000000000000 F
0G
0H
b000 I
0J
0K
0L
b00000 M
b00000 N
b00000 O
b00000000000000000000000000000000 P
b00000000000000000000000000000000 Q
b00000000000000000000000000000000 R
b0000000 S
b00000000000000000000000000000000 T
b00000000000000000000000000000000 U
b00000000000000000000000000000000 V
1W
0X
b00000000000000000000000000000000 Y
b00000000000000000000000000000000 Z
b00000000000000000000000000000000 [
b00000000000000000000000000100000 \
b00000000000000000000000000000101 ]
b00000000000000000000000000001000 ^
#1
b00001111111100000000001100010011 E
b00000000000000000000000011111111 F
1G
1H
1J
b11111 N
b00110 O
b00000000000000000000000011111111 Q
b00000000000000000000000011111111 R
b0010011 S
b00000000000000000000000011111111 T
b00000000000000000000000000000100 U
b00000000000000000000000000000100 V
0W
#2
b00000000000000000000000011111111 $
b00000000000000000000000011111111 +
b00000000000000000000010100010011 E
b00000000000000000000000000000000 F
b00000 N
b01010 O
b00000000000000000000000000000000 Q
b00000000000000000000000000000000 R
b00000000000000000000000000000100 T
b00000000000000000000000000001000 U
b00000000000000000000000000001000 V
1W
b00000000000000000000000000000100 Z
#3
0W
#4
b00000000000000000000010110010011 E
b01011 O
b00000000000000000000000000001000 T
b00000000000000000000000000001100 U
b00000000000000000000000000001100 V
1W
b00000000000000000000000000001000 Z
#5
0W
#6
b00000000000001011000010100010011 E
b01011 M
b01010 O
b00000000000000000000000000001100 T
b00000000000000000000000000010000 U
b00000000000000000000000000010000 V
1W
b00000000000000000000000000001100 Z
#7
0W
#8
b00000000000101011000010110010011 E
b00000000000000000000000000000001 F
b00001 N
b01011 O
b00000000000000000000000000000001 Q
b00000000000000000000000000000001 R
b00000000000000000000000000010001 T
b00000000000000000000000000010100 U
b00000000000000000000000000010100 V
1W
b00000000000000000000000000010000 Z
#9
0W
#10
b00000000000000000000000000000001 #
b00000000000000000000000000000001 0
b11111110011001011001110011100011 E
b11111111111111111111111111111000 F
0G
0H
b001 I
0J
1K
b00110 N
b11001 O
b00000000000000000000000000000001 P
b00000000000000000000000011111111 Q
b00000000000000000000000000000000 R
b1100011 S
b00000000000000000000000000001100 T
b00000000000000000000000000011000 U
b00000000000000000000000000001100 V
1W
b00000000000000000000000000010100 Z
b00000000000000000000000011111111 [
#11
0W
#12
b00000000000001011000010100010011 E
b00000000000000000000000000000000 F
1G
1H
b000 I
1J
0K
b00000 N
b01010 O
b00000000000000000000000000000000 Q
b00000000000000000000000000000001 R
b0010011 S
b00000000000000000000000000010000 U
b00000000000000000000000000010000 V
1W
b00000000000000000000000000001100 Z
b00000000000000000000000000000000 [
#13
0W
#14
b00000000000000000000000000000001 /
b00000000000101011000010110010011 E
b00000000000000000000000000000001 F
b00001 N
b01011 O
b00000000000000000000000000000001 Q
b00000000000000000000000000000010 R
b00000000000000000000000000010001 T
b00000000000000000000000000010100 U
b00000000000000000000000000010100 V
1W
b00000000000000000000000000000001 Y
b00000000000000000000000000010000 Z
#15
0W
#16
b00000000000000000000000000000010 #
b00000000000000000000000000000010 0
b11111110011001011001110011100011 E
b11111111111111111111111111111000 F
0G
0H
b001 I
0J
1K
b00110 N
b11001 O
b00000000000000000000000000000010 P
b00000000000000000000000011111111 Q
b00000000000000000000000000000000 R
b1100011 S
b00000000000000000000000000001100 T
b00000000000000000000000000011000 U
b00000000000000000000000000001100 V
1W
b00000000000000000000000000010100 Z
b00000000000000000000000011111111 [
#17
0W
#18
b00000000000001011000010100010011 E
b00000000000000000000000000000000 F
1G
1H
b000 I
1J
0K
b00000 N
b01010 O
b00000000000000000000000000000000 Q
b00000000000000000000000000000010 R
b0010011 S
b00000000000000000000000000010000 U
b00000000000000000000000000010000 V
1W
b00000000000000000000000000001100 Z
b00000000000000000000000000000000 [
#19
0W
#20
b00000000000000000000000000000010 /
b00000000000101011000010110010011 E
b00000000000000000000000000000001 F
b00001 N
b01011 O
b00000000000000000000000000000001 Q
b00000000000000000000000000000011 R
b00000000000000000000000000010001 T
b00000000000000000000000000010100 U
b00000000000000000000000000010100 V
1W
b00000000000000000000000000000010 Y
b00000000000000000000000000010000 Z
#21
0W
#22
b00000000000000000000000000000011 #
b00000000000000000000000000000011 0
b11111110011001011001110011100011 E
b11111111111111111111111111111000 F
0G
0H
b001 I
0J
1K
b00110 N
b11001 O
b00000000000000000000000000000011 P
b00000000000000000000000011111111 Q
b00000000000000000000000000000000 R
b1100011 S
b00000000000000000000000000001100 T
b00000000000000000000000000011000 U
b00000000000000000000000000001100 V
1W
b00000000000000000000000000010100 Z
b00000000000000000000000011111111 [
#23
0W
#24
b00000000000001011000010100010011 E
b00000000000000000000000000000000 F
1G
1H
b000 I
1J
0K
b00000 N
b01010 O
b00000000000000000000000000000000 Q
b00000000000000000000000000000011 R
b0010011 S
b00000000000000000000000000010000 U
b00000000000000000000000000010000 V
1W
b00000000000000000000000000001100 Z
b00000000000000000000000000000000 [
#25
0W
#26
b00000000000000000000000000000011 /
b00000000000101011000010110010011 E
b00000000000000000000000000000001 F
b00001 N
b01011 O
b00000000000000000000000000000001 Q
b00000000000000000000000000000100 R
b00000000000000000000000000010001 T
b00000000000000000000000000010100 U
b00000000000000000000000000010100 V
1W
b00000000000000000000000000000011 Y
b00000000000000000000000000010000 Z
#27
0W
#28
b00000000000000000000000000000100 #
b00000000000000000000000000000100 0
b11111110011001011001110011100011 E
b11111111111111111111111111111000 F
0G
0H
b001 I
0J
1K
b00110 N
b11001 O
b00000000000000000000000000000100 P
b00000000000000000000000011111111 Q
b00000000000000000000000000000000 R
b1100011 S
b00000000000000000000000000001100 T
b00000000000000000000000000011000 U
b00000000000000000000000000001100 V
1W
b00000000000000000000000000010100 Z
b00000000000000000000000011111111 [
#29
0W
#30
b00000000000001011000010100010011 E
b00000000000000000000000000000000 F
1G
1H
b000 I
1J
0K
b00000 N
b01010 O
b00000000000000000000000000000000 Q
b00000000000000000000000000000100 R
b0010011 S
b00000000000000000000000000010000 U
b00000000000000000000000000010000 V
1W
b00000000000000000000000000001100 Z
b00000000000000000000000000000000 [
#31
0W
#32
b00000000000000000000000000000100 /
b00000000000101011000010110010011 E
b00000000000000000000000000000001 F
b00001 N
b01011 O
b00000000000000000000000000000001 Q
b00000000000000000000000000000101 R
b00000000000000000000000000010001 T
b00000000000000000000000000010100 U
b00000000000000000000000000010100 V
1W
b00000000000000000000000000000100 Y
b00000000000000000000000000010000 Z
#33
0W
#34
b00000000000000000000000000000101 #
b00000000000000000000000000000101 0
b11111110011001011001110011100011 E
b11111111111111111111111111111000 F
0G
0H
b001 I
0J
1K
b00110 N
b11001 O
b00000000000000000000000000000101 P
b00000000000000000000000011111111 Q
b00000000000000000000000000000000 R
b1100011 S
b00000000000000000000000000001100 T
b00000000000000000000000000011000 U
b00000000000000000000000000001100 V
1W
b00000000000000000000000000010100 Z
b00000000000000000000000011111111 [
#35
0W
#36
b00000000000001011000010100010011 E
b00000000000000000000000000000000 F
1G
1H
b000 I
1J
0K
b00000 N
b01010 O
b00000000000000000000000000000000 Q
b00000000000000000000000000000101 R
b0010011 S
b00000000000000000000000000010000 U
b00000000000000000000000000010000 V
1W
b00000000000000000000000000001100 Z
b00000000000000000000000000000000 [
#37
0W
#38
b00000000000000000000000000000101 /
b00000000000101011000010110010011 E
b00000000000000000000000000000001 F
b00001 N
b01011 O
b00000000000000000000000000000001 Q
b00000000000000000000000000000110 R
b00000000000000000000000000010001 T
b00000000000000000000000000010100 U
b00000000000000000000000000010100 V
1W
b00000000000000000000000000000101 Y
b00000000000000000000000000010000 Z
#39
0W
#40
b00000000000000000000000000000110 #
b00000000000000000000000000000110 0
b11111110011001011001110011100011 E
b11111111111111111111111111111000 F
0G
0H
b001 I
0J
1K
b00110 N
b11001 O
b00000000000000000000000000000110 P
b00000000000000000000000011111111 Q
b00000000000000000000000000000000 R
b1100011 S
b00000000000000000000000000001100 T
b00000000000000000000000000011000 U
b00000000000000000000000000001100 V
1W
b00000000000000000000000000010100 Z
b00000000000000000000000011111111 [
#41
0W
#42
b00000000000001011000010100010011 E
b00000000000000000000000000000000 F
1G
1H
b000 I
1J
0K
b00000 N
b01010 O
b00000000000000000000000000000000 Q
b00000000000000000000000000000110 R
b0010011 S
b00000000000000000000000000010000 U
b00000000000000000000000000010000 V
1W
b00000000000000000000000000001100 Z
b00000000000000000000000000000000 [
#43
0W
#44
b00000000000000000000000000000110 /
b00000000000101011000010110010011 E
b00000000000000000000000000000001 F
b00001 N
b01011 O
b00000000000000000000000000000001 Q
b00000000000000000000000000000111 R
b00000000000000000000000000010001 T
b00000000000000000000000000010100 U
b00000000000000000000000000010100 V
1W
b00000000000000000000000000000110 Y
b00000000000000000000000000010000 Z
#45
0W
#46
b00000000000000000000000000000111 #
b00000000000000000000000000000111 0
b11111110011001011001110011100011 E
b11111111111111111111111111111000 F
0G
0H
b001 I
0J
1K
b00110 N
b11001 O
b00000000000000000000000000000111 P
b00000000000000000000000011111111 Q
b00000000000000000000000000000000 R
b1100011 S
b00000000000000000000000000001100 T
b00000000000000000000000000011000 U
b00000000000000000000000000001100 V
1W
b00000000000000000000000000010100 Z
b00000000000000000000000011111111 [
#47
0W
#48
b00000000000001011000010100010011 E
b00000000000000000000000000000000 F
1G
1H
b000 I
1J
0K
b00000 N
b01010 O
b00000000000000000000000000000000 Q
b00000000000000000000000000000111 R
b0010011 S
b00000000000000000000000000010000 U
b00000000000000000000000000010000 V
1W
b00000000000000000000000000001100 Z
b00000000000000000000000000000000 [
#49
0W
#50
b00000000000000000000000000000111 /
b00000000000101011000010110010011 E
b00000000000000000000000000000001 F
b00001 N
b01011 O
b00000000000000000000000000000001 Q
b00000000000000000000000000001000 R
b00000000000000000000000000010001 T
b00000000000000000000000000010100 U
b00000000000000000000000000010100 V
1W
b00000000000000000000000000000111 Y
b00000000000000000000000000010000 Z
#51
0W
#52
b00000000000000000000000000001000 #
b00000000000000000000000000001000 0
b11111110011001011001110011100011 E
b11111111111111111111111111111000 F
0G
0H
b001 I
0J
1K
b00110 N
b11001 O
b00000000000000000000000000001000 P
b00000000000000000000000011111111 Q
b00000000000000000000000000000000 R
b1100011 S
b00000000000000000000000000001100 T
b00000000000000000000000000011000 U
b00000000000000000000000000001100 V
1W
b00000000000000000000000000010100 Z
b00000000000000000000000011111111 [
#53
0W
#54
b00000000000001011000010100010011 E
b00000000000000000000000000000000 F
1G
1H
b000 I
1J
0K
b00000 N
b01010 O
b00000000000000000000000000000000 Q
b00000000000000000000000000001000 R
b0010011 S
b00000000000000000000000000010000 U
b00000000000000000000000000010000 V
1W
b00000000000000000000000000001100 Z
b00000000000000000000000000000000 [
#55
0W
#56
b00000000000000000000000000001000 /
b00000000000101011000010110010011 E
b00000000000000000000000000000001 F
b00001 N
b01011 O
b00000000000000000000000000000001 Q
b00000000000000000000000000001001 R
b00000000000000000000000000010001 T
b00000000000000000000000000010100 U
b00000000000000000000000000010100 V
1W
b00000000000000000000000000001000 Y
b00000000000000000000000000010000 Z
#57
0W
#58
b00000000000000000000000000001001 #
b00000000000000000000000000001001 0
b11111110011001011001110011100011 E
b11111111111111111111111111111000 F
0G
0H
b001 I
0J
1K
b00110 N
b11001 O
b00000000000000000000000000001001 P
b00000000000000000000000011111111 Q
b00000000000000000000000000000000 R
b1100011 S
b00000000000000000000000000001100 T
b00000000000000000000000000011000 U
b00000000000000000000000000001100 V
1W
b00000000000000000000000000010100 Z
b00000000000000000000000011111111 [
#59
0W
#60
b00000000000001011000010100010011 E
b00000000000000000000000000000000 F
1G
1H
b000 I
1J
0K
b00000 N
b01010 O
b00000000000000000000000000000000 Q
b00000000000000000000000000001001 R
b0010011 S
b00000000000000000000000000010000 U
b00000000000000000000000000010000 V
1W
b00000000000000000000000000001100 Z
b00000000000000000000000000000000 [
#61
0W
#62
b00000000000000000000000000001001 /
b00000000000101011000010110010011 E
b00000000000000000000000000000001 F
b00001 N
b01011 O
b00000000000000000000000000000001 Q
b00000000000000000000000000001010 R
b00000000000000000000000000010001 T
b00000000000000000000000000010100 U
b00000000000000000000000000010100 V
1W
b00000000000000000000000000001001 Y
b00000000000000000000000000010000 Z
#63
0W
#64
b00000000000000000000000000001010 #
b00000000000000000000000000001010 0
b11111110011001011001110011100011 E
b11111111111111111111111111111000 F
0G
0H
b001 I
0J
1K
b00110 N
b11001 O
b00000000000000000000000000001010 P
b00000000000000000000000011111111 Q
b00000000000000000000000000000000 R
b1100011 S
b00000000000000000000000000001100 T
b00000000000000000000000000011000 U
b00000000000000000000000000001100 V
1W
b00000000000000000000000000010100 Z
b00000000000000000000000011111111 [
#65
0W
#66
b00000000000001011000010100010011 E
b00000000000000000000000000000000 F
1G
1H
b000 I
1J
0K
b00000 N
b01010 O
b00000000000000000000000000000000 Q
b00000000000000000000000000001010 R
b0010011 S
b00000000000000000000000000010000 U
b00000000000000000000000000010000 V
1W
b00000000000000000000000000001100 Z
b00000000000000000000000000000000 [
#67
0W
#68
b00000000000000000000000000001010 /
b00000000000101011000010110010011 E
b00000000000000000000000000000001 F
b00001 N
b01011 O
b00000000000000000000000000000001 Q
b00000000000000000000000000001011 R
b00000000000000000000000000010001 T
b00000000000000000000000000010100 U
b00000000000000000000000000010100 V
1W
b00000000000000000000000000001010 Y
b00000000000000000000000000010000 Z
#69
0W
#70
b00000000000000000000000000001011 #
b00000000000000000000000000001011 0
b11111110011001011001110011100011 E
b11111111111111111111111111111000 F
0G
0H
b001 I
0J
1K
b00110 N
b11001 O
b00000000000000000000000000001011 P
b00000000000000000000000011111111 Q
b00000000000000000000000000000000 R
b1100011 S
b00000000000000000000000000001100 T
b00000000000000000000000000011000 U
b00000000000000000000000000001100 V
1W
b00000000000000000000000000010100 Z
b00000000000000000000000011111111 [
#71
0W
#72
b00000000000001011000010100010011 E
b00000000000000000000000000000000 F
1G
1H
b000 I
1J
0K
b00000 N
b01010 O
b00000000000000000000000000000000 Q
b00000000000000000000000000001011 R
b0010011 S
b00000000000000000000000000010000 U
b00000000000000000000000000010000 V
1W
b00000000000000000000000000001100 Z
b00000000000000000000000000000000 [
#73
0W
#74
b00000000000000000000000000001011 /
b00000000000101011000010110010011 E
b00000000000000000000000000000001 F
b00001 N
b01011 O
b00000000000000000000000000000001 Q
b00000000000000000000000000001100 R
b00000000000000000000000000010001 T
b00000000000000000000000000010100 U
b00000000000000000000000000010100 V
1W
b00000000000000000000000000001011 Y
b00000000000000000000000000010000 Z
#75
0W
