rtl/single_cycle/program_counter/pc_reg.sv
module pc_reg #(
    parameter WIDTH = 32
)(
    input   logic               clk,    // clock
    /* verilator lint_off UNUSED */
    input   logic               rst,    // reset
    /* verilator lint_on UNUSED */


    input   logic   [WIDTH-1:0] pcin,   // 32-bit input pc
    output  logic   [WIDTH-1:0] pcout   // 32-bit output pc
);

    logic   [WIDTH-1:0]           PCreg;    // 32-bit register

    always_ff @(posedge clk)
    begin
        PCreg <= pcin;      // removed rst setting pc to 0
    end

    assign pcout = PCreg; // fixed pc delay

endmodule

rtl/single_cycle/program_counter/pc_module.sv
module pc_module #(
    parameter WIDTH = 32
)(
    input   logic               clk,    // clock
    input   logic               rst,    // reset
    input   logic   [WIDTH-1:0] ImmOp,  // 32-bit immediate to make a pc jump
    input   logic               PCsrc,  // determined whether pc is +4 or +ImmOp
    output  logic   [WIDTH-1:0] PC      // program counter
);

    logic   [WIDTH-1:0]           branch_PC;    // branch pc ie. pc + immop
    logic   [WIDTH-1:0]           inc_PC;       // increased pc ie. pc + 4
    logic   [WIDTH-1:0]           next_PC;      // next program counter

always_comb begin
    if (rst)
        next_PC <= 32'b0; // resolved wrong value after reset problem
    else begin
        branch_PC <= PC + ImmOp;
        inc_PC <= PC + 32'd4;
        next_PC <= (PCsrc) ? branch_PC : inc_PC;
    end
end

pc_reg mypc_reg (
    .clk (clk),
    .rst (rst),
    .pcin (next_PC),
    .pcout (PC)
);

endmodule

rtl/single_cycle/program_counter/trace.vcd
$version Generated by VerilatedVcd $end
$date Sun Nov 19 14:13:25 2023 $end
$timescale 1ps $end

 $scope module TOP $end
  $var wire 32 ( ImmOp [31:0] $end
  $var wire 32 * PC [31:0] $end
  $var wire  1 ) PCsrc $end
  $var wire  1 & clk $end
  $var wire  1 ' rst $end
  $scope module pc_module $end
   $var wire 32 ( ImmOp [31:0] $end
   $var wire 32 * PC [31:0] $end
   $var wire  1 ) PCsrc $end
   $var wire 32 , WIDTH [31:0] $end
   $var wire 32 # branch_PC [31:0] $end
   $var wire  1 & clk $end
   $var wire 32 $ inc_PC [31:0] $end
   $var wire 32 % next_PC [31:0] $end
   $var wire  1 ' rst $end
   $scope module mypc_reg $end
    $var wire 32 + PCreg [31:0] $end
    $var wire 32 , WIDTH [31:0] $end
    $var wire  1 & clk $end
    $var wire 32 % pcin [31:0] $end
    $var wire 32 * pcout [31:0] $end
    $var wire  1 ' rst $end
   $upscope $end
  $upscope $end
 $upscope $end
$enddefinitions $end


#0
b00000000000000000000000000000000 #
b00000000000000000000000000000100 $
b00000000000000000000000000000100 %
0&
1'
b00000000000000000000000000000000 (
0)
b00000000000000000000000000000000 *
b00000000000000000000000000000000 +
b00000000000000000000000000100000 ,
#10
1&
#20
0&
#30
1&
#40
0&
#50
1&
#60
0&
#70
1&
#80
0&
#90
1&
#100
b00000000000000000000000000100001 #
b00000000000000000000000000011010 $
b00000000000000000000000000100001 %
0&
0'
b00000000000000000000000000001011 (
1)
b00000000000000000000000000010110 *
b00000000000000000000000000100001 +
#110
b00000000000000000000000000101100 #
b00000000000000000000000000100101 $
b00000000000000000000000000101100 %
1&
b00000000000000000000000000100001 *
#120
0&
#130
1&
b00000000000000000000000000101100 +
#140
0&
#150
b00000000000000000000000000110111 #
b00000000000000000000000000110000 $
b00000000000000000000000000110111 %
1&
b00000000000000000000000000101100 *
#160
0&
#170
1&
b00000000000000000000000000110111 +
#180
0&
#190
b00000000000000000000000001000010 #
b00000000000000000000000000111011 $
b00000000000000000000000001000010 %
1&
b00000000000000000000000000110111 *
#200
0&
#210
1&
b00000000000000000000000001000010 +
#220
0&
#230
b00000000000000000000000001001101 #
b00000000000000000000000001000110 $
b00000000000000000000000001001101 %
1&
b00000000000000000000000001000010 *
#240
0&
#250
1&
b00000000000000000000000001001101 +
#260
0&
#270
b00000000000000000000000001011000 #
b00000000000000000000000001010001 $
b00000000000000000000000001011000 %
1&
b00000000000000000000000001001101 *
#280
0&
#290
1&
b00000000000000000000000001011000 +
#300
0&
#310
b00000000000000000000000001100011 #
b00000000000000000000000001011100 $
b00000000000000000000000001100011 %
1&
b00000000000000000000000001011000 *
#320
0&
#330
1&
b00000000000000000000000001100011 +
#340
0&
#350
b00000000000000000000000001101110 #
b00000000000000000000000001100111 $
b00000000000000000000000001101110 %
1&
b00000000000000000000000001100011 *
#360
0&
#370
1&
b00000000000000000000000001101110 +
#380
0&
#390
b00000000000000000000000001111001 #
b00000000000000000000000001110010 $
b00000000000000000000000001111001 %
1&
b00000000000000000000000001101110 *
#400
0&
#410
1&
b00000000000000000000000001111001 +
#420
0&
#430
b00000000000000000000000010000100 #
b00000000000000000000000001111101 $
b00000000000000000000000010000100 %
1&
b00000000000000000000000001111001 *
#440
0&
#450
1&
b00000000000000000000000010000100 +
#460
0&
#470
b00000000000000000000000010001111 #
b00000000000000000000000010001000 $
b00000000000000000000000010001111 %
1&
b00000000000000000000000010000100 *
#480
0&
#490
1&
b00000000000000000000000010001111 +
